{"mc":{
	"r_g1":{
		"frameRate":20,
		"events":[
			
			],
		"frames":[
			
			{
			"res":"88547416",
			"x":60,
			"y":154
			},
			{
			"res":"969045BD",
			"x":60,
			"y":148
			},
			{
			"res":"319E910C",
			"x":60,
			"y":141
			},
			{
			"res":"330187B2",
			"x":60,
			"y":147
			},
			{
			"res":"BDB3D5C9",
			"x":60,
			"y":153
			},
			{
			"res":"6268F95F",
			"x":60,
			"y":147
			},
			{
			"res":"319E910C",
			"x":60,
			"y":141
			},
			{
			"res":"4DC63180",
			"x":60,
			"y":146
			},
			{
			"res":"C22C1910",
			"x":60,
			"y":151
			}
			]
}},
	"res":{
		"88547416":{"x":0,"y":0,"w":153,"h":53},
		"BDB3D5C9":{"x":155,"y":110,"w":153,"h":52},
		"969045BD":{"x":155,"y":0,"w":153,"h":53},
		"4DC63180":{"x":310,"y":0,"w":153,"h":53},
		"C22C1910":{"x":0,"y":55,"w":153,"h":53},
		"330187B2":{"x":155,"y":55,"w":153,"h":53},
		"6268F95F":{"x":310,"y":55,"w":153,"h":53},
		"319E910C":{"x":0,"y":110,"w":153,"h":53}
	}}